reverse_unique/__init__.py
reverse_unique/fields.py
reverse_unique/models.py
reverse_unique_tests/__init__.py
reverse_unique_tests/models.py
reverse_unique_tests/settings.py
reverse_unique_tests/tests.py
django_reverse_unique_charettes-1.1.dist-info/LICENSE
django_reverse_unique_charettes-1.1.dist-info/METADATA
django_reverse_unique_charettes-1.1.dist-info/WHEEL
django_reverse_unique_charettes-1.1.dist-info/top_level.txt
django_reverse_unique_charettes-1.1.dist-info/RECORD
